{
  "main_article": {
    "title": "이찬진 금감원장 \"ELS과징금, 소비자구제·생산적금융 충분히 참작\"",
    "url": "https://n.news.naver.com/mnews/article/088/0000983961"
  },
  "related_articles": [
    {
      "title": "금감원, 홍콩 ELS 판매은행 5곳에 과징금 2조원 사전통지",
      "content": "KB국민은행, 신한은행, 하나은행, NH농협은행, SC제일\n우리은행은 규모 작아 사전통지 대상 빠져\n서울 중구 은행연합회관 앞에서 열린 홍콩지수 ELS 피해자 기자회견. 연합뉴스\n금융감독원이 28일 홍콩H지수(항셍중국기업지수) 주가연계증권(ELS) 불완전 판매에 관해 판매은행 5곳에 합산 과징금 등 약 2조원을 사전 통보한 것으로 파악됐다. 조 단위의 과징금이 그대로 확정될 경우 은행권의 자본비율에도 영향을 미칠 것이라는 관측이 제기된다.\n28일 금융당국과 금융권에 따르면 이날 금감원은 금융소비자보호법 과징금 감독규정에 따른 사전통지서를 각 판매은행에 발송했다. 과징금 및 과태로 부과를 통보받은 은행은 ▷KB국민은행 ▷신한은행 ▷하나은행 ▷NH농협은행 ▷SC제일 등 5곳인 것으로 알려졌다.\n우리은행 역시 판매사이지만, 규모가 가장 작아 사전통지 대상에서는 제외됐다. 은행들의 과징금·과태료의 합산 규모는 약 2조원에 달하는 것으로 전해졌다.\n금융소비자보호법은 금융사가 위법 행위로 얻은 '수입' 또는 이에 준하는 금액의 절반 이내에서 과징금을 부과할 수 있도록 규정한다.\n이에 금융계에서는 금감원이 '수입'을 판매금액과 수수료 중 어떤 것으로 볼 것인지에 관심이 쏠렸다. 과징금 규모를 볼 때 금감원은 우선 판매금액을 기준으로 과징금을 산정한 것으로 보인다.\n금감원은 다음 달 18일 제재심에 해당 안건을 상정하고, 본격 제재 절차를 진행할 예정이다. 과징금 부과 규모는 금융위원회에서 확정된다.",
      "date": "2025.11.28. 오후 3:01",
      "url": "https://n.news.naver.com/mnews/article/088/0000983961",
      "media_from_url": "네이버뉴스"
    }
  ],
  "related_articles_count": 1,
  "analysis": {
    "controversies": [
      {
        "person_name": "금감원",
        "issues": [
          {
            "issue_type": "과징금 부과 대상 선정",
            "details": "홍콩 H지수 ELS 불완전 판매에 대해 5개 은행( KB국민은행, 신한은행, 하나은행, NH농협은행, SC제일) 에 과징금 2조원 사전통지",
            "source": "연합뉴스"
          }
        ]
      },
      {
        "person_name": "KB국민은행",
        "issues": [
          {
            "issue_type": "과징금 부과",
            "details": "과징금 2조원 사전통지 대상",
            "source": "연합뉴스"
          }
        ]
      },
      {
        "person_name": "신한은행",
        "issues": [
          {
            "issue_type": "과징금 부과",
            "details": "과징금 2조원 사전통지 대상",
            "source": "연합뉴스"
          }
        ]
      },
      {
        "person_name": "하나은행",
        "issues": [
          {
            "issue_type": "과징금 부과",
            "details": "과징금 2조원 사전통지 대상",
            "source": "연합뉴스"
          }
        ]
      },
      {
        "person_name": "NH농협은행",
        "issues": [
          {
            "issue_type": "과징금 부과",
            "details": "과징금 2조원 사전통지 대상",
            "source": "연합뉴스"
          }
        ]
      },
      {
        "person_name": "SC제일은행",
        "issues": [
          {
            "issue_type": "과징금 부과",
            "details": "과징금 2조원 사전통지 대상",
            "source": "연합뉴스"
          }
        ]
      }
    ],
    "clarifications": [],
    "evaluations": [
      {
        "source": "금융계",
        "opinion": "과징금 규모가 자본비율에 영향을 미칠 수 있어 우려",
        "stance": "부정적"
      }
    ],
    "facts_vs_allegations": {
      "confirmed_facts": [
        "금감원은 2025년 11월 28일 홍콩 H지수 ELS 불완전 판매에 대해 5개 은행에 과징금 2조원 사전통지",
        "과징금은 판매금액을 기준으로 산정되며, 과징금·과태료의 합산 규모는 약 2조원"
      ],
      "unconfirmed_allegations": [
        "과징금이 실제로 은행의 자본비율에 미칠 영향",
        "과징금이 판매금액과 수수료 중 어떤 것을 기준으로 산정할지에 대한 논란"
      ]
    },
    "timeline": [
      {
        "date": "2025-11-28",
        "event": "금감원이 홍콩 H지수 ELS 불완전 판매에 대해 5개 은행에 과징금 2조원 사전통지"
      },
      {
        "date": "2025-12-18",
        "event": "금감원 제재심에 해당 안건 상정 예정"
      }
    ],
    "youtube_context": [
      {
        "title": "금감원, 홍콩 ELS 판매은행 5곳에 과징금 2조 사전통지 / 연합뉴스TV (YonhapnewsTV)",
        "url": "https://www.youtube.com/watch?v=wXFsndQ6ZGE",
        "link": "https://www.youtube.com/watch?v=wXFsndQ6ZGE",
        "videoId": "wXFsndQ6ZGE",
        "channel": {
          "name": "연합뉴스TV",
          "url": "https://www.youtube.com/@yonhapnewstv23"
        },
        "description": "",
        "publishedAt": "",
        "thumbnail": "",
        "duration": 50.0,
        "viewCount": 228,
        "transcript": ""
      },
      {
        "title": "\"불완전판매 확인\"…홍콩 ELS 판매은행들에 과장금 2조원  / 연합뉴스TV (YonhapnewsTV)",
        "url": "https://www.youtube.com/watch?v=uAOah2YXYpo",
        "link": "https://www.youtube.com/watch?v=uAOah2YXYpo",
        "videoId": "uAOah2YXYpo",
        "channel": {
          "name": "연합뉴스TV",
          "url": "https://www.youtube.com/@yonhapnewstv23"
        },
        "description": "",
        "publishedAt": "",
        "thumbnail": "",
        "duration": 124.0,
        "viewCount": 212,
        "transcript": ""
      },
      {
        "title": "금감원, 홍콩 ELS 판매은행 5곳 과징금 2조원",
        "url": "https://www.youtube.com/watch?v=fZu_ml8aqeE",
        "link": "https://www.youtube.com/watch?v=fZu_ml8aqeE",
        "videoId": "fZu_ml8aqeE",
        "channel": {
          "name": "글로벌금융신문TV",
          "url": "https://www.youtube.com/@TV-fk5lb"
        },
        "description": "",
        "publishedAt": "",
        "thumbnail": "",
        "duration": 144.0,
        "viewCount": 13,
        "transcript": ""
      }
    ],
    "google_context": [
      {
        "title": "4년째 결론 못낸 홍콩 ELS 과징금…금감원, 이르면 내달 제재심 연다 ...",
        "url": "https://www.hankyung.com/article/2025082633941",
        "snippet": "2025. 8. 26. ... 이찬진 원장 취임 후 절차 속도 은행권 과징금 규모에 '촉각'. 이찬진 금융감독원장 취임 후 홍콩 H지수 주가연계증권(ELS) 불완전판매와 관련한 ...",
        "displayLink": "www.hankyung.com"
      },
      {
        "title": "금감원, ELS 과징금 제재심 앞두고…생산적 금융 기조와 충돌 불가피 ...",
        "url": "https://www.investchosun.com/site/data/html_dir/2025/08/29/2025082980194.html",
        "snippet": "2025. 8. 29. ... 이찬진 금감원장, 첫 회동서 '소비자 보호·생산적 금융' 강조 ... 홍콩H지수를 기초자산으로 하는 ELS 총 판매액은 은행권에서 약 16조원에 ...",
        "displayLink": "www.investchosun.com"
      },
      {
        "title": "'홍콩 ELS' 은행 5곳에 과징금 2조원…금감원, 내달 18일 제재심(종합 ...",
        "url": "https://www.news1.kr/finance/general-finance/5991932",
        "snippet": "3일 전 ... (서울=뉴스1) 김근욱 김도엽 기자 = 금융감독원이 홍콩 H지수 주가연계증권(ELS) 불완전 판매 사태와 관련해 주요 시중은행 5곳에 총 2조원 규모의 ...",
        "displayLink": "www.news1.kr"
      },
      {
        "title": "이찬진 금감원장이 '금융소비자 보호 TF' 지시한 까닭은? - 전자부품 ...",
        "url": "https://www.thelec.kr/news/articleView.html?idxno=40319",
        "snippet": "2025. 9. 4. ... TF출범이 ELS(주가연계증권) 불완전판매와도 연결된 만큼 홍콩 H지수 증권 ELS 사태의 과징금 규모에도 관심이 모아진다. 4일 금감원에 따르면 이찬진 ...",
        "displayLink": "www.thelec.kr"
      },
      {
        "title": "4년째 결론 못낸 홍콩 ELS 과징금…금감원, 이르면 내달 제재심 연다",
        "url": "https://v.daum.net/v/20250826171042964?f=p",
        "snippet": "2025. 8. 26. ... 이찬진 금융감독원장 취임 후 홍콩 H지수 주가연계증권(ELS) 불완전판매와 관련한 은행권 과징금 부과 절차에 속도가 붙을 것으로 전망된다. 26일 ...",
        "displayLink": "v.daum.net"
      }
    ]
  },
  "comprehensive_article": null,
  "source_articles": [
    "https://n.news.naver.com/mnews/article/088/0000983961"
  ],
  "timestamp": "2025-12-01T16:40:10.338247",
  "youtube_videos": [
    {
      "title": "금감원, 홍콩 ELS 판매은행 5곳에 과징금 2조 사전통지 / 연합뉴스TV (YonhapnewsTV)",
      "url": "https://www.youtube.com/watch?v=wXFsndQ6ZGE",
      "link": "https://www.youtube.com/watch?v=wXFsndQ6ZGE",
      "videoId": "wXFsndQ6ZGE",
      "channel": {
        "name": "연합뉴스TV",
        "url": "https://www.youtube.com/@yonhapnewstv23"
      },
      "description": "",
      "publishedAt": "",
      "thumbnail": "",
      "duration": 50.0,
      "viewCount": 228,
      "transcript": ""
    },
    {
      "title": "\"불완전판매 확인\"…홍콩 ELS 판매은행들에 과장금 2조원  / 연합뉴스TV (YonhapnewsTV)",
      "url": "https://www.youtube.com/watch?v=uAOah2YXYpo",
      "link": "https://www.youtube.com/watch?v=uAOah2YXYpo",
      "videoId": "uAOah2YXYpo",
      "channel": {
        "name": "연합뉴스TV",
        "url": "https://www.youtube.com/@yonhapnewstv23"
      },
      "description": "",
      "publishedAt": "",
      "thumbnail": "",
      "duration": 124.0,
      "viewCount": 212,
      "transcript": ""
    },
    {
      "title": "금감원, 홍콩 ELS 판매은행 5곳 과징금 2조원",
      "url": "https://www.youtube.com/watch?v=fZu_ml8aqeE",
      "link": "https://www.youtube.com/watch?v=fZu_ml8aqeE",
      "videoId": "fZu_ml8aqeE",
      "channel": {
        "name": "글로벌금융신문TV",
        "url": "https://www.youtube.com/@TV-fk5lb"
      },
      "description": "",
      "publishedAt": "",
      "thumbnail": "",
      "duration": 144.0,
      "viewCount": 13,
      "transcript": ""
    },
    {
      "title": "[Hong Kong ELS Fines] Financial Supervisory Service (FSS) Notifies Banks of KRW 2 Trillion Fines....",
      "url": "https://www.youtube.com/watch?v=zlr6vhV_xJM",
      "link": "https://www.youtube.com/watch?v=zlr6vhV_xJM",
      "videoId": "zlr6vhV_xJM",
      "channel": {
        "name": "초록지기 아재",
        "url": "https://www.youtube.com/@초록지기아재"
      },
      "description": "",
      "publishedAt": "",
      "thumbnail": "",
      "duration": 42.0,
      "viewCount": 0,
      "transcript": ""
    }
  ],
  "youtube_count": 4,
  "google_articles": [
    {
      "title": "4년째 결론 못낸 홍콩 ELS 과징금…금감원, 이르면 내달 제재심 연다 ...",
      "url": "https://www.hankyung.com/article/2025082633941",
      "snippet": "2025. 8. 26. ... 이찬진 원장 취임 후 절차 속도 은행권 과징금 규모에 '촉각'. 이찬진 금융감독원장 취임 후 홍콩 H지수 주가연계증권(ELS) 불완전판매와 관련한 ...",
      "displayLink": "www.hankyung.com"
    },
    {
      "title": "금감원, ELS 과징금 제재심 앞두고…생산적 금융 기조와 충돌 불가피 ...",
      "url": "https://www.investchosun.com/site/data/html_dir/2025/08/29/2025082980194.html",
      "snippet": "2025. 8. 29. ... 이찬진 금감원장, 첫 회동서 '소비자 보호·생산적 금융' 강조 ... 홍콩H지수를 기초자산으로 하는 ELS 총 판매액은 은행권에서 약 16조원에 ...",
      "displayLink": "www.investchosun.com"
    },
    {
      "title": "'홍콩 ELS' 은행 5곳에 과징금 2조원…금감원, 내달 18일 제재심(종합 ...",
      "url": "https://www.news1.kr/finance/general-finance/5991932",
      "snippet": "3일 전 ... (서울=뉴스1) 김근욱 김도엽 기자 = 금융감독원이 홍콩 H지수 주가연계증권(ELS) 불완전 판매 사태와 관련해 주요 시중은행 5곳에 총 2조원 규모의 ...",
      "displayLink": "www.news1.kr"
    },
    {
      "title": "이찬진 금감원장이 '금융소비자 보호 TF' 지시한 까닭은? - 전자부품 ...",
      "url": "https://www.thelec.kr/news/articleView.html?idxno=40319",
      "snippet": "2025. 9. 4. ... TF출범이 ELS(주가연계증권) 불완전판매와도 연결된 만큼 홍콩 H지수 증권 ELS 사태의 과징금 규모에도 관심이 모아진다. 4일 금감원에 따르면 이찬진 ...",
      "displayLink": "www.thelec.kr"
    },
    {
      "title": "4년째 결론 못낸 홍콩 ELS 과징금…금감원, 이르면 내달 제재심 연다",
      "url": "https://v.daum.net/v/20250826171042964?f=p",
      "snippet": "2025. 8. 26. ... 이찬진 금융감독원장 취임 후 홍콩 H지수 주가연계증권(ELS) 불완전판매와 관련한 은행권 과징금 부과 절차에 속도가 붙을 것으로 전망된다. 26일 ...",
      "displayLink": "v.daum.net"
    },
    {
      "title": "신임 금감원장 'ELS 사태' 언급… 최대 8兆 과징금 공포에 떠는 은행 ...",
      "url": "https://biz.chosun.com/stock/finance/2025/09/01/LUKH2IXUIFDV5N6G7USHUU4GSI/",
      "snippet": "2025. 9. 1. ... ... 이찬진 금융감독원장이 국내 은행장과의 첫 만남에서 주가 ... 은행별 홍콩 H지수 ELS 판매금액을 보면, KB국민은행이 8조1972억원으로 ...",
      "displayLink": "biz.chosun.com"
    },
    {
      "title": "금감원, 홍콩 ELS 판매은행 5곳에 2조원 규모 과징금 사전통지-조세 ...",
      "url": "https://m.joseilbo.com/news/view.htm?newsid=557783&class=2",
      "snippet": "3일 전 ... 금감원이 홍콩H지수 ELS 불완전 판매은행 5곳에 2조원 규모의 과징금을 통보한 것으로 확인됐다. [사진=금융감독원]금융감독원이 홍콩H지수 주가연계 ...",
      "displayLink": "m.joseilbo.com"
    },
    {
      "title": "이찬진 \"ELS 과징금, 생산적 금융에 어려움 없도록 노력\" - 아시아경제",
      "url": "https://www.asiae.co.kr/article/2025120113362987195",
      "snippet": "2시간 전 ... 이찬진 금융감독원장은 홍콩H지수 주가연계증권(ELS) 과징금 관련 \"금융 ... 앞서 금감원은 홍콩 ELS 불완전판매와 관련해 KB국민·신한·하나·NH ...",
      "displayLink": "www.asiae.co.kr"
    },
    {
      "title": "금감원, 홍콩H지수 ELS 판매은행 5곳에 '역대 최대' 2조 과징금 사전 ...",
      "url": "https://www.industrynews.co.kr/news/articleView.html?idxno=74898",
      "snippet": "3일 전 ... [인더스트리뉴스 홍윤기 기자] 금융감독원이 홍콩H지수(항셍중국기업지수) 주가연계증권(ELS) 불완전 판매와 관련해 판매은행 5곳에 합산 과징금 약 2 ...",
      "displayLink": "www.industrynews.co.kr"
    },
    {
      "title": "은행권과 첫 상견례 나선 이찬진 금감원장…감독 기조 가늠자 될까 ...",
      "url": "https://news.tf.co.kr/read/economy/2238125.htm",
      "snippet": "2025. 8. 28. ... [더팩트ㅣ이선영 기자] 이찬진 신임 금융감독원장이 28일 은행권 최고경영자들과 첫 간담회를 갖는다. 홍콩 H지수 파생결합증권(ELS) 과징금 부담, 주택 ...",
      "displayLink": "news.tf.co.kr"
    }
  ],
  "google_count": 10
}