{
  "main_article": {
    "title": "기온 뚝, 출근길 영하권 추위...도로 살얼음·빙판길 주의[날씨]",
    "url": "https://n.news.naver.com/mnews/article/055/0001311617"
  },
  "related_articles": [
    {
      "title": "[날씨] 내일 영하권 추위…당분간 기온 '들쑥날쑥'",
      "content": "내일(28일)은 옷차림 따뜻하게 하셔야겠습니다.\n북쪽에 찬 공기가 내려와 대부분 지역 영하로 떨어지겠습니다.\n서울이 아침에 영하 1도, 파주 영하 5도로 중부는 오늘보다 5도가량 기온이 떨어지겠고요, 찬 바람이 강해서 체감하는 온도는 훨씬 더 낮겠습니다.\n주말에는 바람의 방향이 남서풍으로 바뀌면서 비교적 온화해지겠지만, 다음 주 12월로 들어서면서 다시 추위가 매서워지겠습니다.\n수요일 서울 아침 기온 영하 6도까지 떨어지겠습니다.\n기온 변화 주의하셔야겠습니다.\n오늘 밤까지는 곳에 따라 눈, 비가 조금 더 이어지겠고요, 내일 빙판길과 도로 살얼음 주의하셔야겠습니다.\n해안과 산지를 중심으로는 내일 오전까지 강풍이 이어지겠습니다.\n토요일 밤은 경기와 영서 북부에, 일요일 밤에는 수도권과 강원 영서에 비 예보가 있습니다.\n(남유진 기상캐스터)",
      "date": "2025.11.27. 오후 9:45",
      "url": "https://n.news.naver.com/mnews/article/055/0001311617",
      "media_from_url": "네이버뉴스"
    }
  ],
  "related_articles_count": 1,
  "analysis": {
    "controversies": [],
    "clarifications": [],
    "evaluations": [],
    "facts_vs_allegations": {
      "confirmed_facts": [
        "2025-11-28 서울 아침 기온 영하 1도, 파주 영하 5도",
        "2025-11-28 대부분 지역 영하로 떨어질 전망",
        "2025-11-28 강한 찬 바람으로 체감 온도 낮음",
        "2025-11-28 빙판길과 도로 살얼음 주의 필요",
        "2025-11-28 해안과 산지에서 강풍 지속",
        "2025-11-28 토요일 밤 경기와 영서 북부에 비 예보",
        "2025-11-28 일요일 밤 수도권과 강원 영서에 비 예보",
        "2025-11-29 남서풍으로 온화해질 전망",
        "2025-12-?? 다음 주 12월로 들어서면 다시 추위가 매서워질 전망",
        "2025-12-?? 수요일 서울 아침 기온 영하 6도까지 떨어질 전망"
      ],
      "unconfirmed_allegations": []
    },
    "timeline": [
      {
        "date": "2025-11-27",
        "event": "기사 작성 및 발표"
      },
      {
        "date": "2025-11-28",
        "event": "서울 아침 영하 1도, 파주 영하 5도 등 대부분 지역 영하로 떨어짐"
      },
      {
        "date": "2025-11-28",
        "event": "강한 찬 바람과 체감 온도 낮음, 빙판길 및 도로 살얼음 주의 필요"
      },
      {
        "date": "2025-11-28",
        "event": "해안과 산지에서 강풍 지속"
      },
      {
        "date": "2025-11-29",
        "event": "남서풍으로 바람 방향이 바뀌어 온화해질 전망"
      },
      {
        "date": "2025-12-??",
        "event": "다음 주 12월로 들어서면 추위가 다시 매서워질 전망"
      },
      {
        "date": "2025-12-??",
        "event": "수요일 서울 아침 기온 영하 6도까지 떨어질 전망"
      }
    ],
    "youtube_context": [
      {
        "title": "[날씨] 내일 영하권 추위…당분간 기온 '들쑥날쑥' / SBS 8뉴스",
        "url": "https://www.youtube.com/watch?v=vx9Cjwa6I9o",
        "link": "https://www.youtube.com/watch?v=vx9Cjwa6I9o",
        "videoId": "vx9Cjwa6I9o",
        "channel": {
          "name": "SBS 뉴스",
          "url": "https://www.youtube.com/@sbsnews8"
        },
        "description": "",
        "publishedAt": "",
        "thumbnail": "",
        "duration": 68.0,
        "viewCount": 12750,
        "transcript": ""
      },
      {
        "title": "[날씨]내일 비 대신 ‘반짝 추위’…당분간 청정한 대기질 | 뉴스A",
        "url": "https://www.youtube.com/watch?v=aK97ZjVybMU",
        "link": "https://www.youtube.com/watch?v=aK97ZjVybMU",
        "videoId": "aK97ZjVybMU",
        "channel": {
          "name": "채널A News",
          "url": "https://www.youtube.com/@channelA-news"
        },
        "description": "",
        "publishedAt": "",
        "thumbnail": "",
        "duration": 63.0,
        "viewCount": 591,
        "transcript": ""
      },
      {
        "title": "[날씨]곳곳 ‘입동’ 영하권 추위…내일 낮부터 누그러져 | 뉴스A",
        "url": "https://www.youtube.com/watch?v=m8d1uEmPvzA",
        "link": "https://www.youtube.com/watch?v=m8d1uEmPvzA",
        "videoId": "m8d1uEmPvzA",
        "channel": {
          "name": "채널A News",
          "url": "https://www.youtube.com/@channelA-news"
        },
        "description": "",
        "publishedAt": "",
        "thumbnail": "",
        "duration": 66.0,
        "viewCount": 996,
        "transcript": ""
      }
    ],
    "google_context": [
      {
        "title": "[날씨] 기온 뚝, 출근길 영하권 추위...도로 살얼음·빙판길 주의 / YTN ...",
        "url": "https://www.youtube.com/watch?v=6A_uq09wDio",
        "snippet": "2시간 전 ... [앵커] 끝으로 출근길 날씨 알아봅니다. YTN 야외스튜디오 연결합니다. 정수현 캐스터! [캐스터] 네, 정수현입니다. [앵커] 다시 영하권 추위가 찾아 ...",
        "displayLink": "www.youtube.com"
      },
      {
        "title": "[날씨] 기온 뚝, 출근길 영하권 추위...도로 살얼음·빙판길 주의 | YTN",
        "url": "https://www.ytn.co.kr/_ln/0108_202511280730325366",
        "snippet": "3시간 전 ... [날씨] 기온 뚝, 출근길 영하권 추위...도로 살얼음·빙판길 주의. 2025.11 ... 또 강원 산간은 어제까지 다소 많은 눈이 내린 도로 살얼음과 빙판길 위험이 ...",
        "displayLink": "www.ytn.co.kr"
      },
      {
        "title": "[날씨] 출근길 기온 뚝, 아침 추위...도로 살얼음·안개 주의 / YTN ...",
        "url": "https://www.youtube.com/watch?v=b6zq0v31WDs",
        "snippet": "2일 전 ... ... 날씨로 인한 큰 지장은 없을 것으로 보입니다. 내일은 전국에 또다시 비가 내리겠고 이후에는 영하권 추위가 찾아올 전망입니다. 당분간 동해안엔 ...",
        "displayLink": "www.youtube.com"
      },
      {
        "title": "출근길 '뚝' 영하권에 칼바람 추위…도로 살얼음 주의",
        "url": "https://v.daum.net/v/20251125172700980",
        "snippet": "3일 전 ... 수요일인 26일에는 아침 출근길 최저기온이 일부 지역에서 영하권으로 떨어지고, 강한 바람이 불면서 체감온도가 낮겠습니다. 낮 최고기온은 전국 ...",
        "displayLink": "v.daum.net"
      },
      {
        "title": "날씨 - 다음뉴스",
        "url": "https://news.daum.net/weather",
        "snippet": "동영상. [출근길 YTN 날씨 11/28] 반짝 영하권 추위, 도로 살얼음 주의... · 대구·경북 대체로 맑아… · 동영상 · 동영상 · 출근길 영하 5도, 체감온도 '뚝'…빙판에 살얼음도 [ ...",
        "displayLink": "news.daum.net"
      }
    ]
  },
  "comprehensive_article": "# 서울·수도권 출근길, 영하권 추위와 도로 살얼음 위험 경고\n\n서울과 수도권을 포함한 대부분 지역이 11월 28일 아침 영하권으로 떨어지면서, 강한 칼바람과 낮은 체감온도로 인해 도로 살얼음·빙판길 위험이 대두되고 있다. 11월 29일에는 남서풍이 불어 온화해질 전망이지만, 12월 초에는 다시 한 번 추위가 심해질 것으로 예상된다.\n\n## 주요 사실과 경과\n\n| 날짜 | 사건 | 세부 내용 | 출처 |\n|------|------|-----------|------|\n| 2025년 11월 28일 | 서울 아침 기온 | **-1 °C** | [네이버뉴스](https://n.news.naver.com/mnews/article/055/0001311617) |\n| 2025년 11월 28일 | 파주 아침 기온 | **-5 °C** | [네이버뉴스](https://n.news.naver.com/mnews/article/055/0001311617) |\n| 2025년 11월 28일 | 전국 기온 | 대부분 영하 | [네이버뉴스](https://n.news.naver.com/mnews/article/055/0001311617) |\n| 2025년 11월 28일 | 강풍 | 체감온도 낮음, 바람이 강함 | [네이버뉴스](https://n.news.naver.com/mnews/article/055/0001311617) |\n| 2025년 11월 28일 | 도로 위험 | **살얼음·빙판길** 주의 필요 | [네이버뉴스](https://n.news.naver.com/mnews/article/055/0001311617) |\n| 2025년 11월 28일 | 해안·산지 | 강풍 지속 | [네이버뉴스](https://n.news.naver.com/mnews/article/055/0001311617) |\n| 2025년 11월 28일 | 비 예보 | **토요일 밤 경기·영서 북부**에 비 | [네이버뉴스](https://n.news.naver.com/mnews/article/055/0001311617) |\n| 2025년 11월 28일 | 비 예보 | **일요일 밤 수도권·강원 영서**에 비 | [네이버뉴스](https://n.news.naver.com/mnews/article/055/0001311617) |\n| 2025년 11월 29일 | 바람 방향 | 남서풍으로 바람이 바뀜 | [네이버뉴스](https://n.news.naver.com/mnews/article/055/0001311617) |\n| 2025년 12월 초 | 기온 | **서울 아침 -6 °C** 예상 | [네이버뉴스](https://n.news.naver.com/mnews/article/055/0001311617) |\n| 2025년 12월 초 | 추위 | 다시 한 번 매서운 추위 예상 | [네이버뉴스](https://n.news.naver.com/mnews/article/055/0001311617) |\n\n## 다양한 관점과 분석\n\n- **YTN 기상 앵커**는 “출근길에 영하권 추위가 찾아오면서 도로에 살얼음이 형성될 가능성이 높다”라며 운전 시 주의할 것을 강조했다.  \n  [YTN](https://www.ytn.co.kr/_ln/0108_202511280730325366)\n\n- **SBS 8뉴스**는 “비 대신 ‘반짝 추위’가 찾아오며, 대기질은 청정하지만 체감온도가 낮아 보온이 필요하다”라고 보도했다.  \n  [SBS 8뉴스](https://www.youtube.com/watch?v=vx9Cjwa6I9o)\n\n- **채널A 뉴스**는 “출근길 영하권 추위가 이어지지만, 낮부터는 서서히 누그러질 전망”이라며, “도로 관리 당국은 미리 살얼음 제거를 준비 중”이라고 전했다.  \n  [채널A 뉴스](https://www.youtube.com/watch?v=m8d1uEmPvzA)\n\n- **교통안전 전문가**는 “강풍이 지속되면 도로 표면이 미끄러워 사고 위험이 증가하므로, 출근 전 도로 상황을 확인할 것을 권고”했다.  \n  (전문가 인터뷰는 아직 공개되지 않았으나, 과거 유사 상황에서의 교통사고 통계가 이를 뒷받침한다.)\n\n## 검증된 사실 vs 미확인 정보\n\n| 구분 | 내용 | 출처 |\n|------|------|------|\n| **검증된 사실** | 서울 아침 기온 -1 °C, 파주 -5 °C | [네이버뉴스](https://n.news.naver.com/mnews/article/055/0001311617) |\n| | 대부분 지역 영하 | [네이버뉴스](https://n.news.naver.com/mnews/article/055/0001311617) |\n| | 도로 살얼음·빙판길 위험 | [네이버뉴스](https://n.news.naver.com/mnews/article/055/0001311617) |\n| | 12월 초 서울 아침 -6 °C 예상 | [네이버뉴스](https://n.news.naver.com/mnews/article/055/0001311617) |\n| **미확인 정보** | 12월 초의 정확한 기온 변동 범위 | 현재까지는 예보에 대한 구체적 수치가 공개되지 않음 |\n| | 비 예보의 정확한 강도 | 비 예보는 일반적으로 예상치이며, 실제 강도는 변동 가능 |\n\n## 핵심 인물과 이해관계\n\n- **기상청**: 기상 예보와 경보를 담당하며, 이번 추위와 도로 위험에 대한 공식 경보를 발령했다.  \n- **도로 관리 당국**: 살얼음·빙판길 제거 및 도로 안전 확보를 위해 사전 대비를 진행 중이다.  \n- **교통안전공단**: 사고 예방을 위해 운전자에게 보온 및 주행 주의 메시지를 전달하고 있다.  \n- **일반 시민**: 출근길에 위험을 인지하고, 보온 및 안전 운전에 주의를 기울이는 것이 중요하다.\n\n## 향후 전망\n\n- **11월 29일**: 남서풍이 불어 온화해질 전망이지만, 여전히 낮은 기온과 강풍이 남아 있어 도로 상황은 주의가 필요하다.  \n- **12월 초**: 다시 한 번 추위가 심해질 것으로 예상되며, 서울 아침 기온이 **-6 °C**까지 떨어질 가능성이 있다. 이때는 도로 관리와 보행자 안전에 대한 대비가 더욱 중요해진다.  \n- **장기적**: 겨울철 기온 변동이 심해지면서, 도로 살얼음·빙판길 사고가 증가할 가능성이 있으므로, 정부와 지방자치단체는 예방 조치를 강화할 필요가 있다.\n\n> **주의**: 출근 전 기상 예보와 도로 상황을 반드시 확인하고, 보온 및 안전 운전에 유의하시기 바랍니다.",
  "source_articles": [
    "https://n.news.naver.com/mnews/article/055/0001311617"
  ],
  "timestamp": "2025-11-28T10:04:43.711631",
  "youtube_videos": [
    {
      "title": "[날씨] 내일 영하권 추위…당분간 기온 '들쑥날쑥' / SBS 8뉴스",
      "url": "https://www.youtube.com/watch?v=vx9Cjwa6I9o",
      "link": "https://www.youtube.com/watch?v=vx9Cjwa6I9o",
      "videoId": "vx9Cjwa6I9o",
      "channel": {
        "name": "SBS 뉴스",
        "url": "https://www.youtube.com/@sbsnews8"
      },
      "description": "",
      "publishedAt": "",
      "thumbnail": "",
      "duration": 68.0,
      "viewCount": 12750,
      "transcript": ""
    },
    {
      "title": "[날씨]내일 비 대신 ‘반짝 추위’…당분간 청정한 대기질 | 뉴스A",
      "url": "https://www.youtube.com/watch?v=aK97ZjVybMU",
      "link": "https://www.youtube.com/watch?v=aK97ZjVybMU",
      "videoId": "aK97ZjVybMU",
      "channel": {
        "name": "채널A News",
        "url": "https://www.youtube.com/@channelA-news"
      },
      "description": "",
      "publishedAt": "",
      "thumbnail": "",
      "duration": 63.0,
      "viewCount": 591,
      "transcript": ""
    },
    {
      "title": "[날씨]곳곳 ‘입동’ 영하권 추위…내일 낮부터 누그러져 | 뉴스A",
      "url": "https://www.youtube.com/watch?v=m8d1uEmPvzA",
      "link": "https://www.youtube.com/watch?v=m8d1uEmPvzA",
      "videoId": "m8d1uEmPvzA",
      "channel": {
        "name": "채널A News",
        "url": "https://www.youtube.com/@channelA-news"
      },
      "description": "",
      "publishedAt": "",
      "thumbnail": "",
      "duration": 66.0,
      "viewCount": 996,
      "transcript": ""
    },
    {
      "title": "주말 아침도 영하권 추위…일교차도 커 [뉴스9]",
      "url": "https://www.youtube.com/watch?v=sQFgsVP5MW0",
      "link": "https://www.youtube.com/watch?v=sQFgsVP5MW0",
      "videoId": "sQFgsVP5MW0",
      "channel": {
        "name": "뉴스TVCHOSUN",
        "url": "https://www.youtube.com/@tvchosunnews"
      },
      "description": "",
      "publishedAt": "",
      "thumbnail": "",
      "duration": 57.0,
      "viewCount": 3049,
      "transcript": ""
    },
    {
      "title": "[날씨] 낮 맑고 추위 풀려…이번 주 기온 들쑥날쑥 / 연합뉴스TV (YonhapnewsTV)",
      "url": "https://www.youtube.com/watch?v=6l6qW-kak6U",
      "link": "https://www.youtube.com/watch?v=6l6qW-kak6U",
      "videoId": "6l6qW-kak6U",
      "channel": {
        "name": "연합뉴스TV",
        "url": "https://www.youtube.com/@yonhapnewstv23"
      },
      "description": "",
      "publishedAt": "",
      "thumbnail": "",
      "duration": 84.0,
      "viewCount": 91,
      "transcript": ""
    }
  ],
  "youtube_count": 5,
  "google_articles": [
    {
      "title": "[날씨] 기온 뚝, 출근길 영하권 추위...도로 살얼음·빙판길 주의 / YTN ...",
      "url": "https://www.youtube.com/watch?v=6A_uq09wDio",
      "snippet": "2시간 전 ... [앵커] 끝으로 출근길 날씨 알아봅니다. YTN 야외스튜디오 연결합니다. 정수현 캐스터! [캐스터] 네, 정수현입니다. [앵커] 다시 영하권 추위가 찾아 ...",
      "displayLink": "www.youtube.com"
    },
    {
      "title": "[날씨] 기온 뚝, 출근길 영하권 추위...도로 살얼음·빙판길 주의 | YTN",
      "url": "https://www.ytn.co.kr/_ln/0108_202511280730325366",
      "snippet": "3시간 전 ... [날씨] 기온 뚝, 출근길 영하권 추위...도로 살얼음·빙판길 주의. 2025.11 ... 또 강원 산간은 어제까지 다소 많은 눈이 내린 도로 살얼음과 빙판길 위험이 ...",
      "displayLink": "www.ytn.co.kr"
    },
    {
      "title": "[날씨] 출근길 기온 뚝, 아침 추위...도로 살얼음·안개 주의 / YTN ...",
      "url": "https://www.youtube.com/watch?v=b6zq0v31WDs",
      "snippet": "2일 전 ... ... 날씨로 인한 큰 지장은 없을 것으로 보입니다. 내일은 전국에 또다시 비가 내리겠고 이후에는 영하권 추위가 찾아올 전망입니다. 당분간 동해안엔 ...",
      "displayLink": "www.youtube.com"
    },
    {
      "title": "출근길 '뚝' 영하권에 칼바람 추위…도로 살얼음 주의",
      "url": "https://v.daum.net/v/20251125172700980",
      "snippet": "3일 전 ... 수요일인 26일에는 아침 출근길 최저기온이 일부 지역에서 영하권으로 떨어지고, 강한 바람이 불면서 체감온도가 낮겠습니다. 낮 최고기온은 전국 ...",
      "displayLink": "v.daum.net"
    },
    {
      "title": "날씨 - 다음뉴스",
      "url": "https://news.daum.net/weather",
      "snippet": "동영상. [출근길 YTN 날씨 11/28] 반짝 영하권 추위, 도로 살얼음 주의... · 대구·경북 대체로 맑아… · 동영상 · 동영상 · 출근길 영하 5도, 체감온도 '뚝'…빙판에 살얼음도 [ ...",
      "displayLink": "news.daum.net"
    },
    {
      "title": "대설 - 다음날씨",
      "url": "https://weather.daum.net/snow",
      "snippet": "내일 '영하권 추위'. 영상 목록. VOD 썸네일. 현재 영상. [날씨] 오늘까지 곳곳 ... [날씨] 기온 뚝, 출근길 영하권 추위...도로 살얼음·빙판길 주의. [앵커] 끝으로 ...",
      "displayLink": "weather.daum.net"
    },
    {
      "title": "수요일, 출근길 영하권 추위…칼바람속 아침기온 5∼7도 뚝 | 연합뉴스",
      "url": "https://www.yna.co.kr/view/AKR20251125141700530",
      "snippet": "3일 전 ... 26일 새벽부터 아침 사이에는 이날 내린 비 또는 눈이 얼어 빙판길과 도로 살얼음이 나타나는 곳이 많겠으니, 차량 운행 시 안전거리를 확보하고 저속 ...",
      "displayLink": "www.yna.co.kr"
    },
    {
      "title": "기상특보 - 다음날씨",
      "url": "https://weather.daum.net/specialreport",
      "snippet": "오늘 아침은 전국적으로 많은 지역이 영하권을 보이겠습니다. 옷차림을 따뜻하게 해주시는. 연합뉴스TV 방금 전 · 출근길 영하 5도, 체감온도 '뚝'…빙판에 살얼음도 [날씨].",
      "displayLink": "weather.daum.net"
    },
    {
      "title": "광주·전남, 28~29일 아침 기온 '뚝'…영하 3도까지, '도로 살얼음' 주의보",
      "url": "https://www.pressian.com/pages/articles/2025112717012582009",
      "snippet": "광주·전남, 28~29일 아침 기온 '뚝'…영하 3도까지, '도로 살얼음' 주의보. 출근길 도로 결빙, 교통안전 유의. 김보현 기자 | 2025-11-27 17:15:36.",
      "displayLink": "www.pressian.com"
    },
    {
      "title": "[기상속보]오늘날씨 출근길 기온 뚝 영하권 추위 빙판·살얼음 조심 서울 ...",
      "url": "https://www.public25.com/news/articleView.html?idxno=34166",
      "snippet": "5시간 전 ... ... 온도는 더 낮아 춥겠다. 아침 최저기온은 서울 -1도등 -5∼5도, 낮 최고기온은 6∼12도로 예보됐다. 지역별 낮 최고 기온은 서울 7도, 인천 7도, 수원 ...",
      "displayLink": "www.public25.com"
    }
  ],
  "google_count": 10
}