{
  "main_article": {
    "title": "장동혁 \"우리가 갈라져 계엄·탄핵·李정권탄생 못막아…뭉쳐야\"",
    "url": "https://n.news.naver.com/mnews/article/654/0000154007"
  },
  "related_articles": [
    {
      "title": "[속보] 장동혁 \"당 갈라져 이재명 정권 탄생 못막아…하나로 뭉쳐야\"",
      "content": "계엄 1년 앞두고 \"민심 못받들고 민주당 폭주 못막았다…국힘이 부족\"\n양향자, 당 대회서 '계엄 반성' 요구…지지자 항의에 \"다시한번 생각해보라\"\n▲ 국민의힘 장동혁 대표 [연합뉴스 자료사진]\n국민의힘 장동혁 대표가 12·3 비상계엄 사태 1년을 앞둔 29일, 당의 분열을 거듭 비판하며 결집을 촉구했다.\n장 대표는 이날 대전 중구 으능정이 거리에서 열린 '민생 회복 법치수호 대전 국민대회'에서 \"갈라지고 흩어져서, 계엄도, 탄핵도 막지 못했고 이재명 정권의 탄생도 막지 못했다\"고 말했다.\n그는 이어 \"2024년 12월3일 우리는 흩어져 있었다. 2025년 12월3일에는 우리 모두 하나로 뭉쳐있어야 한다\"며 내부 단합의 필요성을 강조했다.\n또 \"국민들께서 지난 정권을 만들어주셨지만 국민의 뜻을 제대로 받들지 못했다. 민주당의 폭주로 나라가 무너지고 있을 때도 제대로 일하지 못했고 하나 되어 막아내지 못했다\"고 밝혔다.\n장 대표는 \"이재명 정권을 퇴장시키기 위해서는 먼저 우리 국민의힘이 바로 서야 한다. 우리가 하나가 되어야만 국민과 함께 싸울 수 있다\"고 말했다. 이는 전날 계엄 사태와 관련한 \"책임 통감\" 발언과 같은 맥락으로, 지도부 사과 요구가 거세지는 분위기에 대한 응답으로도 해석된다. 다만 그는 전날과 마찬가지로 \"민주당의 의회 폭거와 국정 방해가 계엄을 불러왔다\"며 귀책은 민주당에 있다고 주장했다.\n이재명 정부에 대해 장 대표는 \"이재명의 존재 자체가 대한민국의 리스크\", \"민생을 살리고 경제를 일으키려면 이재명과 민주당을 조기 퇴장시키는 수밖에 없다\"고 비판했다.\n또 \"정치보복, 국민 탄압, 방탄 폭정, 민생 파탄의 4종 패키지가 이재명 정권의 뉴노멀\", \"대한민국이 졸지에 삼류 정치 후진국이 됐다\"고 말했다.\n대장동 재판 항소 포기 국정조사와 관련해서는 \"우리 당이 조건 없이 다 받겠다고 하는데도 민주당은 핑계를 대며 도망치기 바쁘다. 진상조사를 기피하는 자가 바로 범인\"이라고 주장했다.\n한편 같은 행사에서 양향자 최고위원은 비상계엄 사태에 대해 공개적으로 반성해야 한다고 말해 주목을 받았다.\n양 최고위원은 \"계엄은 불법이었다. 그 계엄의 불법을 방치한 게 바로 우리 국민의힘이다. 우리는 반성해야 한다\"고 언급했다. 국민의힘 최고위급 인사가 국민대회에서 계엄 문제에 대해 직접적 반성을 공개적으로 밝힌 것은 처음이다.\n현장에서는 일부 지지자들이 고성을 지르거나 커피를 던지는 등 항의가 있었고, 양 최고위원은 이에 \"이런 모습 때문에 국민들이 국민의힘에 신뢰를 안 준다. 저는 이 자리에서 죽어도 좋다. 제 말이 틀리다면 돌팔매를 맞겠다. 그러나 우리가 어떤 대한민국을 만들고자 하는지 다시 생각해야 한다\"고 말했다.",
      "date": "2025.11.29. 오후 4:34",
      "url": "https://n.news.naver.com/mnews/article/654/0000154007",
      "media_from_url": "네이버뉴스"
    }
  ],
  "related_articles_count": 1,
  "analysis": {
    "controversies": [
      {
        "person_name": "장동혁",
        "issues": [
          {
            "issue_type": "정당 분열 비판",
            "details": "장동혁 대표는 2024년 12월 3일 비상계엄 당시 국민의힘이 분열되어 이재명 정권의 탄생을 막지 못했다고 주장",
            "source": "연합뉴스"
          },
          {
            "issue_type": "민주당 책임 주장",
            "details": "민주당이 ‘계엄’과 ‘탄핵’ 등을 불러와 국가가 무너졌다고 비난",
            "source": "연합뉴스"
          },
          {
            "issue_type": "이재명 정권 비판",
            "details": "이재명의 존재 자체를 ‘대한민국의 리스크’라 지칭하고 ‘뉴노멀’ 패키지(정치보복, 국민 탄압, 방탄 폭정, 민생 파탄)를 주장",
            "source": "연합뉴스"
          }
        ]
      },
      {
        "person_name": "양향자",
        "issues": [
          {
            "issue_type": "계엄 반성 요구",
            "details": "양향자 최고위원이 비상계엄 사태에 대해 공개적으로 ‘반성’해야 한다고 주장",
            "source": "연합뉴스"
          }
        ]
      }
    ],
    "clarifications": [
      {
        "person_name": "장동혁",
        "responses": [
          {
            "issue": "민주당의 계엄 불러오기 주장",
            "clarification": "장동혁 대표는 해당 주장을 명확히 재진술했으며, 추가적인 사과나 반성은 제시하지 않았다",
            "date": "2025-11-29"
          }
        ]
      }
    ],
    "evaluations": [
      {
        "source": "연합뉴스",
        "opinion": "기사에서는 장동혁 대표의 주장과 비판을 사실대로 전달하며, 편향적 보도는 없었다",
        "stance": "중립적"
      }
    ],
    "facts_vs_allegations": {
      "confirmed_facts": [
        "2025년 11월 29일 장동혁 대표가 대전에서 국민대회에서 발언",
        "2024년 12월 3일 비상계엄이 선언된 사건",
        "양향자 최고위원이 비상계엄에 대해 ‘반성’해야 한다는 발언"
      ],
      "unconfirmed_allegations": [
        "민주당이 비상계엄을 불러왔다",
        "이재명 정권이 ‘뉴노멀’ 패키지를 실행했다",
        "국민의힘이 계엄에 대해 반성해야 한다",
        "민주당이 진상조사를 기피했다"
      ]
    },
    "timeline": [
      {
        "date": "2024-12-03",
        "event": "비상계엄 선언 및 국민의힘 분열"
      },
      {
        "date": "2025-11-28",
        "event": "장동혁 대표가 ‘책임 통감’ 발언"
      },
      {
        "date": "2025-11-29",
        "event": "장동혁 대표가 대전 국민대회에서 ‘당 분열’과 ‘이재명 정권’ 비판 발언"
      },
      {
        "date": "2025-12-03",
        "event": "비상계엄 1년 기념"
      }
    ],
    "youtube_context": [
      {
        "title": "공개적으로 이재명 대통령 탄핵 외친 장동혁 (ㅋㅋㅋ)",
        "url": "https://www.youtube.com/watch?v=JweV4GSnFl4",
        "videoId": "JweV4GSnFl4",
        "channel": {
          "name": "이마까TV",
          "url": "https://www.youtube.com/channel/UCd6tMX5cbTf6HNf1iug0HrQ"
        },
        "description": "박용진 전의원, 국힘당 김성태와 장동혁에 일갈.",
        "publishedAt": "2025-11-13T11:21:45Z",
        "thumbnail": "https://i.ytimg.com/vi/JweV4GSnFl4/hqdefault.jpg",
        "transcript": ""
      },
      {
        "title": "이재명을 탄핵합시다 장동혁 #이재명 #국민의힘  #장동혁 #이재명탄핵 #항소포기 #대장동",
        "url": "https://www.youtube.com/watch?v=Cmr1TrIFcKs",
        "videoId": "Cmr1TrIFcKs",
        "channel": {
          "name": "정치차렷",
          "url": "https://www.youtube.com/channel/UC0VpQOPxEG0a4ZyHth6XioA"
        },
        "description": "",
        "publishedAt": "2025-11-11T07:46:00Z",
        "thumbnail": "https://i.ytimg.com/vi/Cmr1TrIFcKs/hqdefault.jpg",
        "transcript": ""
      },
      {
        "title": "좌파 유튜버들 제대로 긁는 장동혁 #이재명 #민주당 #장동혁 #좌파 #유튜버",
        "url": "https://www.youtube.com/watch?v=pj8OVAjbfIc",
        "videoId": "pj8OVAjbfIc",
        "channel": {
          "name": "팩트룸",
          "url": "https://www.youtube.com/channel/UCH1Dmx4wb6J1_KLx4QbGOJA"
        },
        "description": "",
        "publishedAt": "2025-11-11T09:35:24Z",
        "thumbnail": "https://i.ytimg.com/vi/pj8OVAjbfIc/hqdefault.jpg",
        "transcript": ""
      }
    ],
    "google_context": [
      {
        "title": "'사과' 못하는 국민의힘‥이젠 \"계엄 민주당 탓\" (2025.11.29/뉴스25 ...",
        "url": "https://www.youtube.com/watch?v=TfnSiHEcV90",
        "snippet": "17시간 전 ... 12.3 비상계엄 1주년을 맞아 국민의힘 내부에선 계엄에 대해 사과해야 한다는 목소리가 잇따르고 있는데요. 이런 가운데 대구를 방문한 장동혁 대표는 ...",
        "displayLink": "www.youtube.com"
      },
      {
        "title": "대구 간 장동혁 “비상계엄, 결과적으로 고통 드렸다” [현장영상]",
        "url": "https://news.kbs.co.kr/news/view.do?ncd=8420123",
        "snippet": "1일 전 ... 국민의힘 장동혁 대표가 지난해 12.3 비상계엄에 대해 \"민주당의 의회 폭거와 국정 방해가 계엄을 불러왔지...",
        "displayLink": "news.kbs.co.kr"
      },
      {
        "title": "장동혁 '사과 머뭇'하자, 당내선 \"우리라도 해야\" 분출 (2025.11.27/뉴스 ...",
        "url": "https://www.youtube.com/watch?v=DdrVirgjrw0",
        "snippet": "2일 전 ... 장동혁 '사과 머뭇'하자, 당내선 \"우리라도 해야\" 분출 (2025.11.27/뉴스데스크/MBC). 13K views · 1 day ago #국민의힘 #장동혁 #비상계엄 ...more ...",
        "displayLink": "www.youtube.com"
      },
      {
        "title": "대구 간 장동혁 “비상계엄, 결과적으로 고통 드렸다” [현장영상]",
        "url": "https://v.daum.net/v/20251128180752988",
        "snippet": "24시간 전 ... 국민의힘 장동혁 대표가 지난해 12.3 비상계엄에 대해 \"민주당의 의회 폭거와 국정 방해가 계엄을 불러왔지만, 결과적으로 많은 국민들께 혼란과 고통 ...",
        "displayLink": "v.daum.net"
      },
      {
        "title": "[정치인싸] '12.3 비상계엄' 1년, 장동혁의 선택은? | 추경호 체포안 가결 ...",
        "url": "https://www.youtube.com/watch?v=oD1YpzQ-zoo",
        "snippet": "6시간 전 ... MBC RADIO 정치인싸 251129 방송 진행: 이정민 아나운서 출연: 윤희석 국민의힘 전 대변인, 박원석 전 의원, 박성태 사람과 사회 연구소 연구실장, ...",
        "displayLink": "www.youtube.com"
      }
    ]
  },
  "comprehensive_article": null,
  "source_articles": [
    "https://n.news.naver.com/mnews/article/654/0000154007"
  ],
  "timestamp": "2025-11-29T18:09:17.573436",
  "youtube_videos": [
    {
      "title": "공개적으로 이재명 대통령 탄핵 외친 장동혁 (ㅋㅋㅋ)",
      "url": "https://www.youtube.com/watch?v=JweV4GSnFl4",
      "videoId": "JweV4GSnFl4",
      "channel": {
        "name": "이마까TV",
        "url": "https://www.youtube.com/channel/UCd6tMX5cbTf6HNf1iug0HrQ"
      },
      "description": "박용진 전의원, 국힘당 김성태와 장동혁에 일갈.",
      "publishedAt": "2025-11-13T11:21:45Z",
      "thumbnail": "https://i.ytimg.com/vi/JweV4GSnFl4/hqdefault.jpg",
      "transcript": ""
    },
    {
      "title": "이재명을 탄핵합시다 장동혁 #이재명 #국민의힘  #장동혁 #이재명탄핵 #항소포기 #대장동",
      "url": "https://www.youtube.com/watch?v=Cmr1TrIFcKs",
      "videoId": "Cmr1TrIFcKs",
      "channel": {
        "name": "정치차렷",
        "url": "https://www.youtube.com/channel/UC0VpQOPxEG0a4ZyHth6XioA"
      },
      "description": "",
      "publishedAt": "2025-11-11T07:46:00Z",
      "thumbnail": "https://i.ytimg.com/vi/Cmr1TrIFcKs/hqdefault.jpg",
      "transcript": ""
    },
    {
      "title": "좌파 유튜버들 제대로 긁는 장동혁 #이재명 #민주당 #장동혁 #좌파 #유튜버",
      "url": "https://www.youtube.com/watch?v=pj8OVAjbfIc",
      "videoId": "pj8OVAjbfIc",
      "channel": {
        "name": "팩트룸",
        "url": "https://www.youtube.com/channel/UCH1Dmx4wb6J1_KLx4QbGOJA"
      },
      "description": "",
      "publishedAt": "2025-11-11T09:35:24Z",
      "thumbnail": "https://i.ytimg.com/vi/pj8OVAjbfIc/hqdefault.jpg",
      "transcript": ""
    },
    {
      "title": "[현장영상+] 장동혁 &quot;민주당과 이재명 정권은 절대 부패 중&quot; / YTN",
      "url": "https://www.youtube.com/watch?v=fXetw0j9Txg",
      "videoId": "fXetw0j9Txg",
      "channel": {
        "name": " YTN",
        "url": "https://www.youtube.com/channel/UChlgI3UHCOnwUGzWzbJ3H5w"
      },
      "description": "[앵커] 민주당 정청래 대표가 교섭단체 연설에서 '내란 청산'에 이어 '국민의힘 해산'까지 거론하자, 장동혁 대표가 긴급 입장 발표에 ...",
      "publishedAt": "2025-09-09T02:52:36Z",
      "thumbnail": "https://i.ytimg.com/vi/fXetw0j9Txg/hqdefault.jpg",
      "transcript": ""
    },
    {
      "title": "이재명 재판 두고 장동혁이 던진 충격적인 말은??",
      "url": "https://www.youtube.com/watch?v=B0BdVok21tc",
      "videoId": "B0BdVok21tc",
      "channel": {
        "name": "시선인사이트",
        "url": "https://www.youtube.com/channel/UCNMCGdrRyaAn5OPmUt3cNgw"
      },
      "description": "정치 #시사 #연예인 #이슈 #뉴스 #배우 #썰 #사건사고 #민주당 #국민의힘 #이재명 #이재명대통령 #장동혁 이재명 재판 두고 장동혁 ...",
      "publishedAt": "2025-11-04T08:00:28Z",
      "thumbnail": "https://i.ytimg.com/vi/B0BdVok21tc/hqdefault.jpg",
      "transcript": ""
    }
  ],
  "youtube_count": 5,
  "google_articles": [
    {
      "title": "'사과' 못하는 국민의힘‥이젠 \"계엄 민주당 탓\" (2025.11.29/뉴스25 ...",
      "url": "https://www.youtube.com/watch?v=TfnSiHEcV90",
      "snippet": "17시간 전 ... 12.3 비상계엄 1주년을 맞아 국민의힘 내부에선 계엄에 대해 사과해야 한다는 목소리가 잇따르고 있는데요. 이런 가운데 대구를 방문한 장동혁 대표는 ...",
      "displayLink": "www.youtube.com"
    },
    {
      "title": "대구 간 장동혁 “비상계엄, 결과적으로 고통 드렸다” [현장영상]",
      "url": "https://news.kbs.co.kr/news/view.do?ncd=8420123",
      "snippet": "1일 전 ... 국민의힘 장동혁 대표가 지난해 12.3 비상계엄에 대해 \"민주당의 의회 폭거와 국정 방해가 계엄을 불러왔지...",
      "displayLink": "news.kbs.co.kr"
    },
    {
      "title": "장동혁 '사과 머뭇'하자, 당내선 \"우리라도 해야\" 분출 (2025.11.27/뉴스 ...",
      "url": "https://www.youtube.com/watch?v=DdrVirgjrw0",
      "snippet": "2일 전 ... 장동혁 '사과 머뭇'하자, 당내선 \"우리라도 해야\" 분출 (2025.11.27/뉴스데스크/MBC). 13K views · 1 day ago #국민의힘 #장동혁 #비상계엄 ...more ...",
      "displayLink": "www.youtube.com"
    },
    {
      "title": "대구 간 장동혁 “비상계엄, 결과적으로 고통 드렸다” [현장영상]",
      "url": "https://v.daum.net/v/20251128180752988",
      "snippet": "24시간 전 ... 국민의힘 장동혁 대표가 지난해 12.3 비상계엄에 대해 \"민주당의 의회 폭거와 국정 방해가 계엄을 불러왔지만, 결과적으로 많은 국민들께 혼란과 고통 ...",
      "displayLink": "v.daum.net"
    },
    {
      "title": "[정치인싸] '12.3 비상계엄' 1년, 장동혁의 선택은? | 추경호 체포안 가결 ...",
      "url": "https://www.youtube.com/watch?v=oD1YpzQ-zoo",
      "snippet": "6시간 전 ... MBC RADIO 정치인싸 251129 방송 진행: 이정민 아나운서 출연: 윤희석 국민의힘 전 대변인, 박원석 전 의원, 박성태 사람과 사회 연구소 연구실장, ...",
      "displayLink": "www.youtube.com"
    },
    {
      "title": "계엄 1년 앞두고 커지는 '사과' 요구…국민의힘 일각 \"장동혁, 尹 절연 ...",
      "url": "https://v.daum.net/v/20251126065615746",
      "snippet": "3일 전 ... 12.3 비상계엄 선포 1년을 앞두고 국민의힘 내에서 '장동혁 지도부'의 강경 노선을 둘러싼 우려·비판의 목소리가 일부 의원을 중심으로 나오고 있다. 계엄 ...",
      "displayLink": "v.daum.net"
    },
    {
      "title": "\"사과 없으면 연판장\"…'계엄의 강' 앞에 선 국민의힘 / SBS - YouTube",
      "url": "https://www.youtube.com/watch?v=K9H33VgU5lc",
      "snippet": "10시간 전 ... 〈앵커〉 다음 주 수요일이 12·3 비상계엄 1년입니다. 국민의힘의 소장파 의원들은 장동혁 대표를 향해 사과를 하지 않으면 연판짱을 돌리겠다며 집단 ...",
      "displayLink": "www.youtube.com"
    },
    {
      "title": "보령시국회의 '장동혁 당 대표 후보 자진 사퇴' 촉구 - 뉴스스토리",
      "url": "http://www.news-story.co.kr/news/articleView.html?idxno=82004",
      "snippet": "2025. 8. 20. ... 보령시국회의가 국민의힘 당 대표로 출마한 장동혁 의원(충남 보령시.서천군)의 자진 사퇴를 촉구하며 나섰다.윤석열 12.3 비상계엄과 탄핵 속 장동혁 ...",
      "displayLink": "www.news-story.co.kr"
    },
    {
      "title": "'계엄의 강' 아니라 '늪'?.. '12월3일' 코앞 자중지란 [뉴스.zip/MBC뉴스]",
      "url": "https://www.youtube.com/watch?v=jCnlLL7re4k",
      "snippet": "9시간 전 ... 국민의힘 #장동혁 #비상계엄 #MBC #뉴스 #뉴스데스크 #MBC뉴스 #뉴스투데이 #뉴스ZIP #뉴스꾹 #오늘이뉴스 #자막뉴스 ㅤ 00:00 장동혁 '사과 머뭇'하자 ...",
      "displayLink": "www.youtube.com"
    },
    {
      "title": "장동혁, 직접적 사과 없이 “계엄 책임 통감” | 채널A 뉴스",
      "url": "https://ichannela.com/news/detail/000000503125.do",
      "snippet": "23시간 전 ... [앵커] “결과적으로 국민께 고통드렸다, 그 책임을 통감한다” 국민의힘 장동혁 대표가 12.3 비상계엄을 두고 처음 입장을 밝혔습니다.",
      "displayLink": "ichannela.com"
    }
  ],
  "google_count": 10
}