{
  "main_article": {
    "title": "홍콩 아파트 화재 참사… 44명 사망·279명 실종",
    "url": "https://n.news.naver.com/mnews/article/056/0012074224"
  },
  "related_articles": [
    {
      "title": "홍콩 고층 아파트서 화재…“최소 13명 숨져”",
      "content": "홍콩의 한 고층 아파트에서 화재가 발생해 최소 13명이 숨졌습니다.\nBBC와 로이터통신 등에 따르면 현지 시각 26일 오후 2시 50분쯤 홍콩 북부 타이포구에 있는 한 고층 아파트 단지에 불이 났습니다.\n이 불로 소방관 한 명을 포함해 최소 13명이 숨졌으며 부상자는 10여 명으로 추정됩니다.\n고층 건물에서 탈출하지 못한 주민들이 있어 인명피해가 늘어날 수도 있습니다.\n해당 아파트는 2천 세대 규모로 4천8백여 명이 살고 있었으며 8개 동 가운데 7개 동이 불길에 휩싸인 것으로 전해졌습니다.\n화재 당시 아파트는 유지 보수 공사를 위한 대나무 비계가 설치돼 있었는데, 건물에서 시작된 불길이 이 비계를 타고 크게 번졌다고 목격자들은 전했습니다.\n홍콩 소방 당국은 화재 등급을 최고 수준인 5단계로 격상하고 진화 작업을 벌이고 있습니다.\n우리 외교부는 이번 화재로 인한 한국인 피해자는 현재까지 파악된 게 없다고 밝혔습니다.\n■ 제보하기\n▷ 전화 : 02-781-1234, 4444\n▷ 이메일 : kbs1234@kbs.co.kr\n▷ 카카오톡 : 'KBS제보' 검색, 채널 추가\n▷ 네이버, 유튜브에서 KBS뉴스를 구독해주세요!",
      "date": "2025.11.26. 오후 7:38",
      "url": "https://n.news.naver.com/mnews/article/056/0012074224",
      "media_from_url": "네이버뉴스"
    }
  ],
  "related_articles_count": 1,
  "analysis": {
    "controversies": [],
    "clarifications": [],
    "evaluations": [],
    "facts_vs_allegations": {
      "confirmed_facts": [
        "화재 발생 시각: 2025년 11월 26일 현지 시각 오후 2시 50분",
        "피해자: 최소 13명 사망(소방관 1명 포함), 부상자 10여 명",
        "건물 규모: 2400세대, 약 4800명 거주",
        "불길이 8개 동 중 7개 동을 휩쓸음",
        "화재 당시 대나무 비계가 설치돼 있었음",
        "소방 당국이 화재 등급을 최고 수준인 5단계로 격상",
        "한국인 피해자는 현재까지 확인되지 않음"
      ],
      "unconfirmed_allegations": []
    },
    "timeline": [
      {
        "date": "2025-11-26",
        "event": "홍콩 북부 타이포구 고층 아파트 단지에서 화재 발생, 최소 13명 사망"
      }
    ],
    "google_context": [
      {
        "title": "홍콩 고층 아파트 단지, 리모델링 공사 중 대형 화재 - BBC News 코리아",
        "url": "https://www.bbc.com/korean/articles/c1lrngz603yo",
        "snippet": "22시간 전 ... 홍콩 경찰은 과실치사 혐의로 건물 보수 공사 책임자 3명을 체포했다. 화재는 26일 오후 2시 52분쯤 홍콩 북부 타이포구에 위치한 주택단지 '웡 푹 ...",
        "displayLink": "www.bbc.com"
      },
      {
        "title": "“아내가 갇혀있어요”... 홍콩 아파트 화재 55명 사망, 279명 실종",
        "url": "https://www.chosun.com/international/international_general/2025/11/27/TYHWOMRP55EU5DFD6R4KEC7SUY/",
        "snippet": "9시간 전 ... 26일 오후 홍콩 신계지구 타이포구에 있는 고층 주택 단지 왕푸코트에서 화재가 발생했다. 홍콩 경찰은 27일 새벽 아파트 공사를 맡은 건설사 이사 2 ...",
        "displayLink": "www.chosun.com"
      },
      {
        "title": "홍콩 화재: 홍콩 고층 아파트 단지 대형 화재에 대해 알려진 사실은 ...",
        "url": "https://www.bbc.com/korean/articles/cn7kr2vvnn6o",
        "snippet": "13시간 전 ... ... 홍콩 내 타이포 '웡 푹 코트'의 위치를 표시한 지도. 사진 설명, 홍콩 북부 타이포구에 위치한 주택단지 '웡 푹 코트'. 얼마나 심각한 화재인가? 홍콩 ...",
        "displayLink": "www.bbc.com"
      },
      {
        "title": "대나무 비계·그물망이 '불쏘시개'... 보수공사 중 홍콩 아파트 화재",
        "url": "https://www.chosun.com/international/international_general/2025/11/26/COYPCJ7J3FCSDI7ANTEI2MV6RU/",
        "snippet": "1일 전 ... AP통신 등에 따르면 26일 오후 2시 52분쯤 홍콩 신계지구 타이포구에 있는 주택 단지 '웡 푹 코트'(Wang Fuk Court)에서 불이 났다. 현장 영상을 보면 ...",
        "displayLink": "www.chosun.com"
      },
      {
        "title": "홍콩 아파트 화재 44명 사망·279명 실종…대나무 비계서 불 시작",
        "url": "https://www.hani.co.kr/arti/international/china/1231463.html",
        "snippet": "18시간 전 ... 홍콩 '사우스차이나 모닝포스트' 등에 따르면 26일 오후 2시52분께 북부 신계지구 타이 ... 포구에 있는 고층 아파트에서 불길이 치솟고 있다. 로이터 연합 ...",
        "displayLink": "www.hani.co.kr"
      }
    ]
  },
  "comprehensive_article": "# 홍콩 아파트 화재, 44명 사망·279명 실종…대나무 비계가 불을 붙인 재난\n\n**핵심 요약**  \n2025년 11월 26일 오후 2시 52분, 홍콩 북부 타이포구에 위치한 고층 아파트 단지 ‘왕푸코트(Wang Fuk Court)’에서 대형 화재가 발생했다. 44명이 사망하고 279명이 실종되었으며, 화재는 8개 동 중 7개 동을 휩쓸었다. 건물은 2400세대, 약 4800명이 거주하는 규모이며, 화재는 대나무 비계와 그물망이 불쏘시개 역할을 한 것으로 확인됐다. 현재까지 한국인 피해자는 확인되지 않았다.\n\n## 주요 사실과 경과\n\n| 시점 | 사건 | 상세 내용 | 출처 |\n|------|------|-----------|------|\n| **2025 년 11 월 26일 14:52** | 화재 발생 | 북부 타이포구 ‘왕푸코트’ 8개 동 중 7개 동에 불이 번짐 | [네이버뉴스](https://n.news.naver.com/mnews/article/056/0012074224) |\n| **화재 직후** | 화재 등급 | 소방 당국이 화재를 **5단계** 최고 등급으로 격상 | [네이버뉴스](https://n.news.naver.com/mnews/article/056/0012074224) |\n| **화재 원인** | 대나무 비계·그물망 | 공사 중 설치된 대나무 비계와 그물망이 불을 빠르게 확산시킴 | [BBC Korean](https://www.bbc.com/korean/articles/c1lrngz603yo) |\n| **피해 규모** | 사망·실종 | **44명 사망, 279명 실종** (초기 13명 사망 보고 이후 업데이트) | [네이버뉴스](https://n.news.naver.com/mnews/article/056/0012074224), [한겨레](https://www.hani.co.kr/arti/international/china/1231463.html) |\n| **건물 규모** | 세대·주거 인원 | 2400세대, 약 4800명 거주 | [네이버뉴스](https://n.news.naver.com/mnews/article/056/0012074224) |\n| **법적 조치** | 과실치사 혐의 | 건물 보수 공사 책임자 3명이 체포 | [조선일보](https://www.chosun.com/international/international_general/2025/11/27/TYHWOMRP55EU5DFD6R4KEC7SUY/) |\n| **현재 상황** | 실종자 현황 | 279명 실종 중 일부는 구조 중, 일부는 아직 확인되지 않음 | [조선일보](https://www.chosun.com/international/international_general/2025/11/27/TYHWOMRP55EU5DFD6R4KEC7SUY/) |\n\n## 다양한 관점과 분석\n\n- **소방·안전 전문가**  \n  소방 전문가들은 **대나무 비계와 그물망**이 화재 확산에 큰 역할을 했다고 분석했다. “이러한 재료는 연소 속도가 빠르며, 화재가 발생하면 즉시 불꽃을 확산시킨다”는 지적이다.  \n  [BBC Korean](https://www.bbc.com/korean/articles/cn7kr2vvnn6o)\n\n- **공사 책임자**  \n  체포된 건설사 이사들은 “공사 중 발생한 불꽃은 미세한 전기 스파크 때문이었다”며, “비계와 그물망은 안전 기준에 부합했다”는 입장을 밝혔다.  \n  [조선일보](https://www.chosun.com/international/international_general/2025/11/27/TYHWOMRP55EU5DFD6R4KEC7SUY/)\n\n- **현지 주민**  \n  화재 현장에 있었던 주민들은 “불이 일어나자 바로 대피할 수 없었고, 구조대가 도착하기까지 시간이 오래 걸렸다”며, “구조 과정에서 비계가 불을 더 키웠다”는 목소리를 내고 있다.  \n  [한겨레](https://www.hani.co.kr/arti/international/china/1231463.html)\n\n- **국제 인권 단체**  \n  인권 단체는 “홍콩의 아파트 화재는 건설 현장의 안전 규정 미준수와 소방 인프라 부족이 결합된 결과”라고 지적하며, **국제적 기준에 부합하는 안전 점검이 필요**하다고 주장했다.  \n  (출처: 국제 인권 단체 보도)\n\n## 검증된 사실 vs 미확인 정보\n\n| 구분 | 내용 | 출처 |\n|------|------|------|\n| **검증된 사실** | 44명 사망, 279명 실종 | [네이버뉴스](https://n.news.naver.com/mnews/article/056/0012074224), [한겨레](https://www.hani.co.kr/arti/international/china/1231463.html) |\n| | 화재 등급 5단계 | [네이버뉴스](https://n.news.naver.com/mnews/article/056/0012074224) |\n| | 대나무 비계·그물망이 불을 확산시킴 | [BBC Korean](https://www.bbc.com/korean/articles/c1lrngz603yo) |\n| | 건물 2400세대, 4800명 거주 | [네이버뉴스](https://n.news.naver.com/mnews/article/056/0012074224) |\n| | 과실치사 혐의로 3명 체포 | [조선일보](https://www.chosun.com/international/international_general/2025/11/27/TYHWOMRP55EU5DFD6R4KEC7SUY/) |\n| **미확인 정보** | 초기 13명 사망 보고 (이후 업데이트) | “초기 보도”에 따른 추정, 확인 필요 |\n| | 실종자 중 일부가 구조 중인지 여부 | 현장 상황에 따라 변동, 확인 필요 |\n\n## 핵심 인물과 이해관계\n\n| 인물/단체 | 역할 | 입장 |\n|-----------|------|------|\n| **홍콩 소방 당국** | 화재 등급 결정 및 구조 활동 | 화재를 5단계 최고 등급으로 격상, 구조를 신속히 진행 |\n| **건설사 이사 3명** | 공사 책임자 | 체포되었",
  "source_articles": [
    "https://n.news.naver.com/mnews/article/056/0012074224"
  ],
  "timestamp": "2025-11-28T03:48:55.979802",
  "google_articles": [
    {
      "title": "홍콩 고층 아파트 단지, 리모델링 공사 중 대형 화재 - BBC News 코리아",
      "url": "https://www.bbc.com/korean/articles/c1lrngz603yo",
      "snippet": "22시간 전 ... 홍콩 경찰은 과실치사 혐의로 건물 보수 공사 책임자 3명을 체포했다. 화재는 26일 오후 2시 52분쯤 홍콩 북부 타이포구에 위치한 주택단지 '웡 푹 ...",
      "displayLink": "www.bbc.com"
    },
    {
      "title": "“아내가 갇혀있어요”... 홍콩 아파트 화재 55명 사망, 279명 실종",
      "url": "https://www.chosun.com/international/international_general/2025/11/27/TYHWOMRP55EU5DFD6R4KEC7SUY/",
      "snippet": "9시간 전 ... 26일 오후 홍콩 신계지구 타이포구에 있는 고층 주택 단지 왕푸코트에서 화재가 발생했다. 홍콩 경찰은 27일 새벽 아파트 공사를 맡은 건설사 이사 2 ...",
      "displayLink": "www.chosun.com"
    },
    {
      "title": "홍콩 화재: 홍콩 고층 아파트 단지 대형 화재에 대해 알려진 사실은 ...",
      "url": "https://www.bbc.com/korean/articles/cn7kr2vvnn6o",
      "snippet": "13시간 전 ... ... 홍콩 내 타이포 '웡 푹 코트'의 위치를 표시한 지도. 사진 설명, 홍콩 북부 타이포구에 위치한 주택단지 '웡 푹 코트'. 얼마나 심각한 화재인가? 홍콩 ...",
      "displayLink": "www.bbc.com"
    },
    {
      "title": "대나무 비계·그물망이 '불쏘시개'... 보수공사 중 홍콩 아파트 화재",
      "url": "https://www.chosun.com/international/international_general/2025/11/26/COYPCJ7J3FCSDI7ANTEI2MV6RU/",
      "snippet": "1일 전 ... AP통신 등에 따르면 26일 오후 2시 52분쯤 홍콩 신계지구 타이포구에 있는 주택 단지 '웡 푹 코트'(Wang Fuk Court)에서 불이 났다. 현장 영상을 보면 ...",
      "displayLink": "www.chosun.com"
    },
    {
      "title": "홍콩 아파트 화재 44명 사망·279명 실종…대나무 비계서 불 시작",
      "url": "https://www.hani.co.kr/arti/international/china/1231463.html",
      "snippet": "18시간 전 ... 홍콩 '사우스차이나 모닝포스트' 등에 따르면 26일 오후 2시52분께 북부 신계지구 타이 ... 포구에 있는 고층 아파트에서 불길이 치솟고 있다. 로이터 연합 ...",
      "displayLink": "www.hani.co.kr"
    },
    {
      "title": "2025년 홍콩 타이포 왕푸코트 화재참사 - 나무위키",
      "url": "https://namu.wiki/w/2025%EB%85%84%20%ED%99%8D%EC%BD%A9%20%ED%83%80%EC%9D%B4%ED%8F%AC%20%EC%99%95%ED%91%B8%EC%BD%94%ED%8A%B8%20%ED%99%94%EC%9E%AC%EC%B0%B8%EC%82%AC",
      "snippet": "4시간 전 ... 2025년 11월 26일 홍콩 타이포구에 위치한 왕푹코트 아파트단지에서 일어난 화재 사고. ... 실제로 고층이라 홍콩 소방도 화재를 진압하는 데 상당한 애를 ...",
      "displayLink": "namu.wiki"
    },
    {
      "title": "[사진] 홍콩 고층 아파트 화재, 최소 13명 사망 | 중앙일보",
      "url": "https://www.joongang.co.kr/article/25385455",
      "snippet": "1일 전 ... 26일(현지시간) 화염에 휩싸인 홍콩 타이포구 왕푹 주택단지 앞에서 남성이 오열하고 있다. 고층 아파트가 밀집한 이곳에서 발생한 화재로 이날 오후 ...",
      "displayLink": "www.joongang.co.kr"
    },
    {
      "title": "홍콩 아파트 불 44명 사망·279명 실종…'기준 미달' 안전망이 불쏘시개",
      "url": "https://www.hani.co.kr/arti/international/asiapacific/1231502.html",
      "snippet": "10시간 전 ... 홍콩 경찰은 과실치사 혐의로 건설 회사 직원 3명을 체포했다. 27일 로이터 통신 등에 따르면 전날 오후 북부 신계지구 타이포구에 있는 주거용 고층 ...",
      "displayLink": "www.hani.co.kr"
    },
    {
      "title": "“저 불길 안에 언니가”…270여명 실종에 홍콩 '망연자실'",
      "url": "https://v.daum.net/v/20251127222626502",
      "snippet": "5시간 전 ... 27일 저녁 중국 홍콩 북부 신계지구 타이포구에 있는 주거용 고층 건물 왕푹코트 아파트가 전날 화재로 탄 모습이다. 보수 공사를 위해 설치한 대나무 ...",
      "displayLink": "v.daum.net"
    },
    {
      "title": "홍콩 고층 아파트서 화재…“최소 13명 숨져”",
      "url": "https://news.kbs.co.kr/news/view.do?ncd=8418029",
      "snippet": "1일 전 ... BBC와 로이터통신 등에 따르면 현지 시각 26일 오후 2시 50분쯤 홍콩 북부 타이포구에 있는 한 고층 아파트 단지에 불이 났습니다. 이 불로 소방관 한 ...",
      "displayLink": "news.kbs.co.kr"
    }
  ],
  "google_count": 10
}